ruuvitag_ble/__init__.py
ruuvitag_ble/df3_decoder.py
ruuvitag_ble/df5_decoder.py
ruuvitag_ble/df6_decoder.py
ruuvitag_ble/parser.py
ruuvitag_ble/py.typed
ruuvitag_ble-0.2.1.dist-info/METADATA
ruuvitag_ble-0.2.1.dist-info/WHEEL
ruuvitag_ble-0.2.1.dist-info/licenses/LICENSE
ruuvitag_ble-0.2.1.dist-info/RECORD
